{"metadata":{"city":"Bardaghat","district":"Nawalpur","province":"Gandaki","last_updated":"2026-03-25","source":"Nepal Police","total_records":3},"emergency":[{"id":1,"name":"Bardaghat Police Station","category":"Police","phone":["100","078-520144"],"address":"Bardaghat, Nawalpur","description":"Local police station"},{"id":2,"name":"Bardaghat Hospital Emergency","category":"Hospital","phone":["078-520100"],"address":"Bardaghat Hospital","description":"24/7 emergency"},{"id":3,"name":"Fire Service","category":"Fire","phone":["101"],"address":"Bardaghat, Nawalpur","description":"Fire emergency"}]}
