{
  "metadata": {
    "city": "Mahendranagar",
    "district": "Kanchanpur",
    "province": "Sudurpashchim",
    "last_updated": "2026-03-25",
    "source": "ANSAB Directory, Department of Forests and Soil Conservation",
    "total_records": 1
  },
  "forest_offices": [
    {
      "id": 1,
      "name": "Division Forest Office Kanchanpur",
      "name_np": "डिभिजन वन कार्यालय कञ्चनपुर",
      "type": "Division Forest Office",
      "address": "Mahendranagar, Kanchanpur",
      "phone": ["099-522427"],
      "district": "Kanchanpur",
      "province": "Sudurpashchim",
      "services": ["Forest Management", "Community Forest", "Wildlife Conservation", "Timber Permits"]
    }
  ]
}
