{
  "metadata": {
    "city": "Pokhara",
    "district": "Kaski",
    "province": "Gandaki",
    "country": "Nepal",
    "last_updated": "2026-03-31",
    "source": "Pokhara University, Gandaki Medical College, Manipal College Official Websites",
    "total_records": 6,
    "note": "Universities and university-affiliated institutions in Pokhara Valley"
  },
  "universities": [
    {
      "id": 1,
      "name": "Pokhara University Central Office",
      "type": "Central University Office",
      "address": "Pokhara University, Dhungepatan, Pokhara-15, Kaski",
      "phone": ["061-504046", "061-504047", "061-504048"],
      "website": "https://www.pu.edu.np/",
      "email": "info@pu.edu.np",
      "district": "Kaski",
      "city": "Pokhara",
      "province": "Gandaki",
      "gps": null,
      "hours": "Sunday-Thursday: 10:00 AM - 5:00 PM",
      "services": ["Examination", "Academic Administration", "Affiliation", "Transcripts"]
    },
    {
      "id": 2,
      "name": "Gandaki Medical College",
      "type": "Medical College",
      "address": "Lekhnath-1, Pokhara, Kaski",
      "phone": ["061-561517", "061-561518", "061-561519"],
      "website": "https://www.gmcpokhara.com/",
      "email": "info@gmcpokhara.com",
      "district": "Kaski",
      "city": "Pokhara",
      "province": "Gandaki",
      "gps": null,
      "hours": "Sunday-Friday: 9:00 AM - 5:00 PM",
      "services": ["MBBS Programs", "Nursing", "Allied Health Sciences", "Medical Services"]
    },
    {
      "id": 3,
      "name": "Manipal College of Medical Sciences",
      "type": "Medical College",
      "address": "Deep Heights, Pokhara, Kaski",
      "phone": ["061-440738", "061-440739", "061-440740"],
      "website": "https://manipalpokhara.edu.np/",
      "email": "info@manipalpokhara.edu.np",
      "district": "Kaski",
      "city": "Pokhara",
      "province": "Gandaki",
      "gps": null,
      "hours": "Sunday-Friday: 9:00 AM - 5:00 PM",
      "services": ["MBBS Programs", "Postgraduate Medical Education", "Dental", "Nursing"]
    },
    {
      "id": 4,
      "name": "Pokhara Engineering College",
      "type": "Engineering College",
      "address": "Phirke, Pokhara-7, Kaski",
      "phone": ["061-446073", "061-446074"],
      "website": "https://pec.edu.np/",
      "email": "info@pec.edu.np",
      "district": "Kaski",
      "city": "Pokhara",
      "province": "Gandaki",
      "gps": null,
      "hours": "Sunday-Friday: 9:00 AM - 5:00 PM",
      "services": ["Engineering Programs", "Diploma Courses", "Technical Education"]
    },
    {
      "id": 5,
      "name": "Soch College of IT",
      "type": "IT College",
      "address": "Zero Kilometer, Pokhara, Kaski",
      "phone": ["061-536969", "061-536970"],
      "website": "https://www.sochit.edu.np/",
      "email": "info@sochit.edu.np",
      "district": "Kaski",
      "city": "Pokhara",
      "province": "Gandaki",
      "gps": null,
      "hours": "Sunday-Friday: 9:00 AM - 5:00 PM",
      "services": ["BCA Programs", "BIT Programs", "Computer Science"]
    },
    {
      "id": 6,
      "name": "Institute of Forestry, Pokhara Campus",
      "type": "Specialized Institute",
      "address": "Hariyokharka, Pokhara-15, Kaski",
      "phone": ["061-504144", "061-504145"],
      "website": "https://iof.pu.edu.np/",
      "email": "iofpu@pu.edu.np",
      "district": "Kaski",
      "city": "Pokhara",
      "province": "Gandaki",
      "gps": null,
      "hours": "Sunday-Friday: 9:00 AM - 5:00 PM",
      "services": ["Forestry Education", "Environmental Science", "Research"]
    }
  ]
}
