{
  "metadata": {
    "city": "Pokhara",
    "district": "Kaski",
    "province": "Gandaki",
    "country": "Nepal",
    "last_updated": "2026-03-31",
    "source": "Gandaki Provincial Hospital, Pokhara Academy of Health Sciences, Private Hospital Websites",
    "total_records": 18,
    "note": "Major hospitals and medical centers in Pokhara metropolitan area"
  },
  "hospitals": [
    {
      "id": 1,
      "name": "Gandaki Provincial Hospital",
      "type": "Public",
      "address": "Ramghat, Pokhara",
      "phone": ["061-520666", "061-520667"],
      "website": "https://gandakihospital.gov.np/",
      "email": "info@gandakihospital.gov.np",
      "district": "Kaski",
      "city": "Pokhara",
      "gps": null,
      "beds": 300,
      "emergency": true,
      "services": ["General Medicine", "Surgery", "Pediatrics", "Gynecology", "Orthopedics", "Emergency"]
    },
    {
      "id": 2,
      "name": "Pokhara Academy of Health Sciences (PAHS)",
      "type": "Public",
      "address": "Fulbari, Pokhara",
      "phone": ["061-504067", "061-504068"],
      "website": "https://pahs.edu.np/",
      "email": "info@pahs.edu.np",
      "district": "Kaski",
      "city": "Pokhara",
      "gps": null,
      "beds": 350,
      "emergency": true,
      "services": ["General Medicine", "Surgery", "Cardiology", "Neurology", "Cancer Care", "Teaching Hospital"]
    },
    {
      "id": 3,
      "name": "Manipal Teaching Hospital",
      "type": "Private",
      "address": "Phulbari, Pokhara",
      "phone": ["061-526416", "061-526417"],
      "website": "https://manipalpokhara.com/",
      "email": "info@manipalpokhara.com",
      "district": "Kaski",
      "city": "Pokhara",
      "gps": null,
      "beds": 750,
      "emergency": true,
      "services": ["General Medicine", "Surgery", "Cardiology", "Neurology", "Orthopedics", "Cancer Care", "Emergency"]
    },
    {
      "id": 4,
      "name": "Charak Memorial Hospital",
      "type": "Private",
      "address": "Sabhagriha Chowk, Pokhara",
      "phone": ["061-521842", "061-521843"],
      "website": "https://charakhospital.com/",
      "email": "info@charakhospital.com",
      "district": "Kaski",
      "city": "Pokhara",
      "gps": null,
      "beds": 100,
      "emergency": true,
      "services": ["General Medicine", "Surgery", "Gynecology", "Pediatrics", "Emergency"]
    },
    {
      "id": 5,
      "name": "Fewa City Hospital",
      "type": "Private",
      "address": "Srijanachowk, Pokhara",
      "phone": ["061-538481", "061-538482"],
      "website": null,
      "email": null,
      "district": "Kaski",
      "city": "Pokhara",
      "gps": null,
      "beds": 50,
      "emergency": true,
      "services": ["General Medicine", "Surgery", "Emergency"]
    },
    {
      "id": 6,
      "name": "Metro City Hospital",
      "type": "Private",
      "address": "Mahendrapool, Pokhara",
      "phone": ["061-538444", "061-538445"],
      "website": null,
      "email": null,
      "district": "Kaski",
      "city": "Pokhara",
      "gps": null,
      "beds": 75,
      "emergency": true,
      "services": ["General Medicine", "Surgery", "Gynecology", "Emergency"]
    },
    {
      "id": 7,
      "name": "Pokhara City Hospital",
      "type": "Private",
      "address": "Nayabazar, Pokhara",
      "phone": ["061-521555", "061-521556"],
      "website": null,
      "email": null,
      "district": "Kaski",
      "city": "Pokhara",
      "gps": null,
      "beds": 60,
      "emergency": true,
      "services": ["General Medicine", "Surgery", "Emergency"]
    },
    {
      "id": 8,
      "name": "Om Hospital & Research Center",
      "type": "Private",
      "address": "Chipledhunga, Pokhara",
      "phone": ["061-537200", "061-537201"],
      "website": "https://omhospitalpokhara.com/",
      "email": "info@omhospitalpokhara.com",
      "district": "Kaski",
      "city": "Pokhara",
      "gps": null,
      "beds": 150,
      "emergency": true,
      "services": ["General Medicine", "Surgery", "Cardiology", "Orthopedics", "Emergency"]
    },
    {
      "id": 9,
      "name": "Fishtail Hospital",
      "type": "Private",
      "address": "Gairapatan, Pokhara",
      "phone": ["061-464457", "061-464458"],
      "website": null,
      "email": null,
      "district": "Kaski",
      "city": "Pokhara",
      "gps": null,
      "beds": 80,
      "emergency": true,
      "services": ["General Medicine", "Surgery", "Gynecology", "Emergency"]
    },
    {
      "id": 10,
      "name": "Green City Hospital",
      "type": "Private",
      "address": "Bagar, Pokhara",
      "phone": ["061-534444", "061-534445"],
      "website": null,
      "email": null,
      "district": "Kaski",
      "city": "Pokhara",
      "gps": null,
      "beds": 40,
      "emergency": true,
      "services": ["General Medicine", "Surgery", "Emergency"]
    },
    {
      "id": 11,
      "name": "Lake City Hospital",
      "type": "Private",
      "address": "Lakeside, Pokhara",
      "phone": ["061-463333", "061-463334"],
      "website": null,
      "email": null,
      "district": "Kaski",
      "city": "Pokhara",
      "gps": null,
      "beds": 35,
      "emergency": false,
      "services": ["General Medicine", "Minor Surgery"]
    },
    {
      "id": 12,
      "name": "Prithvi Narayan Shah Hospital",
      "type": "Private",
      "address": "Mahendrapool, Pokhara",
      "phone": ["061-521234", "061-521235"],
      "website": null,
      "email": null,
      "district": "Kaski",
      "city": "Pokhara",
      "gps": null,
      "beds": 50,
      "emergency": true,
      "services": ["General Medicine", "Surgery", "Emergency"]
    },
    {
      "id": 13,
      "name": "Himalayan Eye Hospital",
      "type": "Specialized",
      "address": "Gyaneshwor, Pokhara",
      "phone": ["061-520088", "061-520089"],
      "website": null,
      "email": null,
      "district": "Kaski",
      "city": "Pokhara",
      "gps": null,
      "beds": 30,
      "emergency": false,
      "services": ["Eye Care", "Ophthalmology", "Eye Surgery"]
    },
    {
      "id": 14,
      "name": "Pokhara Nursing Home",
      "type": "Private",
      "address": "New Road, Pokhara",
      "phone": ["061-522222", "061-522223"],
      "website": null,
      "email": null,
      "district": "Kaski",
      "city": "Pokhara",
      "gps": null,
      "beds": 25,
      "emergency": false,
      "services": ["General Medicine", "Maternity"]
    },
    {
      "id": 15,
      "name": "Shree Krishna Hospital",
      "type": "Private",
      "address": "Birauta, Pokhara",
      "phone": ["061-538888", "061-538889"],
      "website": null,
      "email": null,
      "district": "Kaski",
      "city": "Pokhara",
      "gps": null,
      "beds": 45,
      "emergency": true,
      "services": ["General Medicine", "Surgery", "Emergency"]
    },
    {
      "id": 16,
      "name": "Gandaki Medical College Teaching Hospital",
      "type": "Private",
      "address": "Lekhnath, Pokhara",
      "phone": ["061-561200", "061-561201"],
      "website": "https://gandakimedicalcollege.edu.np/",
      "email": "info@gandakimedicalcollege.edu.np",
      "district": "Kaski",
      "city": "Pokhara",
      "gps": null,
      "beds": 500,
      "emergency": true,
      "services": ["General Medicine", "Surgery", "Cardiology", "Neurology", "Teaching Hospital", "Emergency"]
    },
    {
      "id": 17,
      "name": "Western Regional Hospital",
      "type": "Public",
      "address": "Ramghat, Pokhara",
      "phone": ["061-520100", "061-520101"],
      "website": null,
      "email": null,
      "district": "Kaski",
      "city": "Pokhara",
      "gps": null,
      "beds": 150,
      "emergency": true,
      "services": ["General Medicine", "Surgery", "Emergency", "Referral Center"]
    },
    {
      "id": 18,
      "name": "Pokhara Cancer Hospital",
      "type": "Specialized",
      "address": "Fulbari, Pokhara",
      "phone": ["061-504500", "061-504501"],
      "website": null,
      "email": null,
      "district": "Kaski",
      "city": "Pokhara",
      "gps": null,
      "beds": 80,
      "emergency": false,
      "services": ["Cancer Treatment", "Radiotherapy", "Chemotherapy", "Oncology"]
    }
  ]
}
